mgz2imgslices/__init__.py
mgz2imgslices/__main__.py
mgz2imgslices/mgz2imgslices.py
mgz2imgslices-2.1.3.dist-info/LICENSE
mgz2imgslices-2.1.3.dist-info/METADATA
mgz2imgslices-2.1.3.dist-info/WHEEL
mgz2imgslices-2.1.3.dist-info/entry_points.txt
mgz2imgslices-2.1.3.dist-info/top_level.txt
mgz2imgslices-2.1.3.dist-info/RECORD
