Metadata-Version: 2.1
Name: mgz2imgslices
Version: 2.1.3
Summary: (Python) utility to filter mgz volumes to per-voxel-value directories of jpg/png image slices
Home-page: https://github.com/FNNDSC/mgz2imgslices
Author: FNNDSC
Author-email: dev@babymri.org
License: MIT
License-File: LICENSE
Requires-Dist: pfmisc
Requires-Dist: nibabel
Requires-Dist: numpy
Requires-Dist: matplotlib
Requires-Dist: pillow
Requires-Dist: pandas
Requires-Dist: imageio
Requires-Dist: scikit-image
